setup.py
client/__init__.py
client/client_app.py
client/client/__init__.py
client/client/add_contact.py
client/client/client_database.py
client/client/client_gui.py
client/client/main_window_client.py
client/client/start_dialog.py
client/common/__init__.py
client/common/decos.py
client/common/descriptors.py
client/common/errors.py
client/common/metaclasses.py
client/common/settings.py
client/common/utils.py
client/log/__init__.py
client/log/configs/__init__.py
client/log/configs/client_log_config.py
client/tests/__init__.py
client/tests/test_client.py
client/tests/test_server.py
client/tests/test_utils.py
client_app.egg-info/PKG-INFO
client_app.egg-info/SOURCES.txt
client_app.egg-info/dependency_links.txt
client_app.egg-info/requires.txt
client_app.egg-info/top_level.txt