Metadata-Version: 1.0
Name: client-app
Version: 0.0.2
Summary: client_app
Home-page: UNKNOWN
Author: Aleksey Ostryakov
Author-email: test@yandex.ru
License: UNKNOWN
Platform: UNKNOWN
